trajectory_vis/__init__.py
trajectory_vis/camera.py
trajectory_vis/game_objects.py
trajectory_vis/utils.py
trajectory_vis/visualizers/__init__.py
trajectory_vis/visualizers/visualizer.py
trajectory_vis/visualizers/visualizer_from_drain_db.py
trajectory_vis/visualizers/visualizer_from_json.py
trajectory_vis-1.0.0.dist-info/METADATA
trajectory_vis-1.0.0.dist-info/WHEEL
trajectory_vis-1.0.0.dist-info/top_level.txt
trajectory_vis-1.0.0.dist-info/RECORD
