Metadata-Version: 2.1
Name: trajectory-vis
Version: 1.0.0
Summary: Visualization of data and/or model trajectories on a 2D plane using pygame
Home-page: https://gitlab-ncsa.ubisoft.org/tboulet/trajectory-visualization
Author: tboulet
Author-email: timothe.boulet0@gmail.com
License: MIT
Requires-Dist: pygame
